tkpygame/__init__.py
tkpygame/button.py
tkpygame/canvas.py
tkpygame/constants.py
tkpygame/inputfield.py
tkpygame/label.py
tkpygame/listbox.py
tkpygame/screen.py
tkpygame/utils.py
tkpygame-0.2.0.dist-info/LICENSE
tkpygame-0.2.0.dist-info/METADATA
tkpygame-0.2.0.dist-info/WHEEL
tkpygame-0.2.0.dist-info/top_level.txt
tkpygame-0.2.0.dist-info/RECORD
