Metadata-Version: 2.1
Name: tkpygame
Version: 0.2.0
Summary: A custom Tkinter-Pygame module.
Home-page: https://github.com/lexxnl/tkpygame
Author: Lex Kimmel
Author-email: lex.kimmel@gmail.com
License: MIT
Classifier: Programming Language :: Python :: 3
Classifier: License :: OSI Approved :: MIT License
Classifier: Operating System :: OS Independent
Requires-Python: >=3.6
License-File: LICENSE
Requires-Dist: pygame
Requires-Dist: Pillow
